kernelsfabian/__init__.py
kernelsfabian/kernels.py
Libkernelsfabian-0.1.0.dist-info/METADATA
Libkernelsfabian-0.1.0.dist-info/WHEEL
Libkernelsfabian-0.1.0.dist-info/top_level.txt
Libkernelsfabian-0.1.0.dist-info/RECORD
