Metadata-Version: 2.1
Name: Libkernelsfabian
Version: 0.1.0
Summary: diferentes suavizados en esta librería
Home-page: UNKNOWN
Author: Fabian
Author-email: fyamith.tovar@udea.edu.co
License: MIT
Platform: UNKNOWN
Requires-Python: >=3.10.12
Requires-Dist: matplotlib (==3.8.1)
Requires-Dist: numpy (==1.26.2)
Requires-Dist: pandas (==2.1.3)
